soundwave/__init__.py
soundwave/main.py
soundwave-0.0.6.dist-info/LICENSE.txt
soundwave-0.0.6.dist-info/METADATA
soundwave-0.0.6.dist-info/WHEEL
soundwave-0.0.6.dist-info/top_level.txt
soundwave-0.0.6.dist-info/RECORD
