Metadata-Version: 2.1
Name: soundwave
Version: 0.0.6
Summary: UNKNOWN
Home-page: UNKNOWN
Author: SHAPTARSHI GHOSH
Author-email: __________@gmail.com
License: MIT
Platform: UNKNOWN
Classifier: Programming Language :: Python :: 3
Classifier: License :: OSI Approved :: MIT License
Classifier: Operating System :: OS Independent
License-File: LICENSE.txt
